cashmere/__init__.py
cashmere/__main__.py
cashmere/_version.py
cashmere/autoserial.py
cashmere/backends.py
cashmere/cli.py
cashmere/constants.py
cashmere/core.py
cashmere/serializers.py
cashmere/utils.py
cashmere-0.1.8.dist-info/AUTHORS.rst
cashmere-0.1.8.dist-info/LICENSE
cashmere-0.1.8.dist-info/METADATA
cashmere-0.1.8.dist-info/WHEEL
cashmere-0.1.8.dist-info/entry_points.txt
cashmere-0.1.8.dist-info/top_level.txt
cashmere-0.1.8.dist-info/RECORD
